graphpro/__init__.py
graphpro/annotations.py
graphpro/collection.py
graphpro/graph.py
graphpro/graphgen.py
graphpro/model.py
graphpro/util/conservation.py
graphpro/util/dssp.py
graphpro/util/energy.py
graphpro/util/modes.py
graphpro/util/polarity.py
graphpro/util/residues.py
graphpro/util/sasa.py
graphpro-0.24.0.dist-info/METADATA
graphpro-0.24.0.dist-info/WHEEL
graphpro-0.24.0.dist-info/licenses/LICENSE.txt
graphpro-0.24.0.dist-info/RECORD
