Metadata-Version: 2.4
Name: graphpro
Version: 0.24.0
Dynamic: Requires-Dist
Summary: A python module to handle graph protein data
Project-URL: Homepage, https://github.com/pegerto/graphpro
Project-URL: Bug Tracker, https://github.com/pegerto/graphpro
Author-email: Pegerto Fernandez <pegerto@gmail.com>
License-File: LICENSE.txt
Classifier: License :: OSI Approved :: GNU General Public License v3 (GPLv3)
Classifier: Operating System :: OS Independent
Classifier: Programming Language :: Python :: 3
Classifier: Topic :: Scientific/Engineering
Classifier: Topic :: Scientific/Engineering :: Artificial Intelligence
Classifier: Topic :: Scientific/Engineering :: Bio-Informatics
Requires-Python: >=3.7
